LICENSE
MANIFEST.in
README.rst
setup.py
MockMockMock/__init__.py
MockMockMock/arguments_checking.py
MockMockMock/expectation_handling.py
MockMockMock/replacer.py
MockMockMock.egg-info/PKG-INFO
MockMockMock.egg-info/SOURCES.txt
MockMockMock.egg-info/dependency_links.txt
MockMockMock.egg-info/top_level.txt
MockMockMock/expectation_grouping/__init__.py
MockMockMock/expectation_grouping/completion_policies.py
MockMockMock/expectation_grouping/ordering_policies.py
MockMockMock/tests/__init__.py
MockMockMock/tests/arguments_checking.py
MockMockMock/tests/expectation_sequence.py
MockMockMock/tests/grouping.py
MockMockMock/tests/ordering.py
MockMockMock/tests/public_interface.py
MockMockMock/tests/record_replay.py
MockMockMock/tests/sequence_of_independent_mocks.py
MockMockMock/tests/sequence_of_linked_mocks.py
MockMockMock/tests/single_expectation.py
MockMockMock/tests/single_expectation_not_called.py
MockMockMock/tests/system_calls.py